MotionSense/MotionDetector.py
MotionSense/__init__.py
MotionSense-0.1.0.dist-info/METADATA
MotionSense-0.1.0.dist-info/WHEEL
MotionSense-0.1.0.dist-info/top_level.txt
MotionSense-0.1.0.dist-info/RECORD
