Metadata-Version: 2.1
Name: MotionSense
Version: 0.1.0
Summary: A Python library for Motion Detection
Author: Lyova
Author-email: lev.avyan17@gmail.com
Requires-Dist: numpy
Requires-Dist: opencv-python
